{
  "folder": "polXxU4IYXTzgmFD",
  "name": "Electrobolter",
  "type": "upgrade",
  "_id": "rDUqCX6s7PplH3y5",
  "img": "systems/essence20/assets/icons/items/upgrade_weapon.svg",
  "system": {
    "originalId": "",
    "description": "",
    "source": {
      "book": "Transformers Core Rulebook",
      "page": 129
    },
    "armorBonus": {
      "defense": "toughness",
      "value": 0
    },
    "availability": "restricted",
    "benefit": "",
    "traits": [
      "electric"
    ],
    "type": "weapon",
    "prerequisite": ""
  },
  "effects": [],
  "flags": {},
  "_stats": {
    "systemId": "essence20",
    "systemVersion": "4.1.2",
    "coreVersion": "12.331",
    "createdTime": 1695684969277,
    "modifiedTime": 1704127422538,
    "lastModifiedBy": "ai0LSR3ikAGU2SmG",
    "compendiumSource": null,
    "duplicateSource": null
  },
  "sort": 0,
  "ownership": {
    "default": 0
  },
  "_key": "!items!rDUqCX6s7PplH3y5"
}
