{
  "name": "Hardened",
  "icon": "icons/svg/aura.svg",
  "origin": "Compendium.essence20.tf_crb.Item.sWnZEyr6M1I5ciDr",
  "duration": {
    "startTime": null,
    "seconds": null,
    "combat": null,
    "rounds": null,
    "turns": null,
    "startRound": null,
    "startTurn": null
  },
  "disabled": false,
  "_id": "cbYu0iFG9YGRP9rM",
  "changes": [
    {
      "key": "system.health.bonus",
      "mode": 2,
      "value": "1"
    }
  ],
  "description": "",
  "transfer": true,
  "statuses": [],
  "flags": {},
  "tint": null,
  "_key": "!items.effects!sWnZEyr6M1I5ciDr.cbYu0iFG9YGRP9rM"
}