{
  "folder": "wbMaXGb3TtcwbBFy",
  "name": "Driving Strike",
  "type": "perk",
  "_id": "bP55ciUhiMJzyTGC",
  "img": "systems/essence20/assets/icons/items/perk.svg",
  "system": {
    "originalId": "",
    "description": "",
    "source": {
      "book": "Finster's Monster-Matic Cookbook",
      "page": 286
    },
    "prerequisite": "",
    "selectionLimit": 1,
    "type": "role"
  },
  "effects": [],
  "sort": 100000,
  "ownership": {
    "default": 0,
    "TfzSCNLMDHUjSABQ": 3
  },
  "flags": {},
  "_stats": {
    "systemId": "essence20",
    "systemVersion": "4.2.0",
    "coreVersion": "12.323",
    "createdTime": 1713667987450,
    "modifiedTime": 1714865642982,
    "lastModifiedBy": "VEn5sPQRoWgUw9qd",
    "compendiumSource": null,
    "duplicateSource": null
  },
  "_key": "!items!bP55ciUhiMJzyTGC"
}
