{
  "type": "Item",
  "folder": null,
  "name": "Factions",
  "color": null,
  "sorting": "a",
  "_id": "vFjqmIue75mhktmd",
  "description": "",
  "sort": 0,
  "flags": {},
  "_stats": {
    "compendiumSource": null,
    "duplicateSource": null,
    "exportSource": null,
    "coreVersion": "13.344",
    "systemId": "essence20",
    "systemVersion": "4.6.9",
    "createdTime": 1749079700756,
    "modifiedTime": 1749079708062,
    "lastModifiedBy": "j6WWLUdptyfr6qBb"
  },
  "_key": "!folders!vFjqmIue75mhktmd"
}
