{
  "name": "Out of Touch",
  "type": "hangUp",
  "img": "icons/svg/hazard.svg",
  "system": {
    "originalId": "",
    "description": "",
    "source": {
      "book": "My Little Pony Core Rulebook",
      "page": 49
    }
  },
  "effects": [],
  "flags": {
    "core": {}
  },
  "_stats": {
    "systemId": "essence20",
    "systemVersion": "4.1.2",
    "coreVersion": "13.344",
    "createdTime": 1680142918658,
    "modifiedTime": 1704127413367,
    "lastModifiedBy": "ai0LSR3ikAGU2SmG",
    "compendiumSource": null,
    "duplicateSource": null,
    "exportSource": null
  },
  "_id": "GjOvI88JglH8yukq",
  "folder": "ly03UXfH1Jdy7p6W",
  "sort": 0,
  "ownership": {
    "default": 0
  },
  "_key": "!items!GjOvI88JglH8yukq"
}
