{
  "folder": "agZ0btQpymAY7YIq",
  "name": "Brawling Alternate Effect 1",
  "type": "weaponEffect",
  "_id": "JK2fJIoMMEmrX3pF",
  "img": "systems/essence20/assets/icons/items/weapon_effect.svg",
  "system": {
    "originalId": "",
    "classification": {
      "skill": "might",
      "style": "melee"
    },
    "damageType": "blunt",
    "damageValue": 1,
    "shiftDown": 2,
    "numHands": "0",
    "numTargets": 1,
    "radius": 0,
    "range": {
      "min": null,
      "reachMultiplier": 0,
      "long": null,
      "value": null
    }
  },
  "effects": [],
  "sort": 100000,
  "ownership": {
    "default": 0
  },
  "flags": {},
  "_stats": {
    "systemId": "essence20",
    "systemVersion": "3.3.0",
    "coreVersion": "11.307",
    "createdTime": 1695834954397,
    "modifiedTime": 1695886918139,
    "lastModifiedBy": "RQsfT4GIto0XIK1k"
  },
  "_key": "!items!JK2fJIoMMEmrX3pF"
}