{
  "folder": "ePKUlzLeh1NeQ3rK",
  "name": "Power Blaster",
  "type": "weapon",
  "_id": "XOHIHF5fK2MeJ2Wh",
  "img": "systems/essence20/assets/icons/weapons/pistol.svg",
  "system": {
    "originalId": "",
    "description": "<p>Energy x Power Weapons</p>",
    "source": {
      "book": "Core Book",
      "page": 108
    },
    "classFeatureId": null,
    "alternateEffects": "",
    "availability": "limited",
    "equipped": true,
    "requirements": {
      "custom": "Combined Weapon",
      "skill": "athletics",
      "shift": "none"
    },
    "traits": [
      "energy"
    ],
    "upgradeIds": [],
    "upgradeTraits": [],
    "usesPerScene": null,
    "weaponEffectIds": [
      "1CaJmAanGDVL3pY3"
    ],
    "classification": {
      "size": "medium"
    }
  },
  "effects": [],
  "sort": 0,
  "ownership": {
    "default": 0
  },
  "flags": {},
  "_stats": {
    "systemId": "essence20",
    "systemVersion": "3.3.0",
    "coreVersion": "11.307",
    "createdTime": 1696145916718,
    "modifiedTime": 1696181299696,
    "lastModifiedBy": "RQsfT4GIto0XIK1k"
  },
  "_key": "!items!XOHIHF5fK2MeJ2Wh"
}