{
  "folder": "kvf1ZslntELicto6",
  "name": "Thrown Blade Alternate Effect 1",
  "type": "weaponEffect",
  "_id": "HAV5XHqgTKQ36Liz",
  "img": "systems/essence20/assets/icons/items/weapon_effect.svg",
  "system": {
    "originalId": "",
    "classification": {
      "skill": "targeting",
      "style": "projectile"
    },
    "damageType": "maneuver",
    "damageValue": null,
    "shiftDown": 2,
    "numHands": "1",
    "numTargets": 1,
    "radius": 0,
    "range": {
      "min": null,
      "reachMultiplier": 0,
      "long": 30,
      "value": 20
    }
  },
  "effects": [],
  "flags": {
    "core": {},
    "essence20": {}
  },
  "_stats": {
    "systemId": "essence20",
    "systemVersion": "4.1.2",
    "coreVersion": "11.315",
    "createdTime": 1695398793019,
    "modifiedTime": 1704127419815,
    "lastModifiedBy": "ai0LSR3ikAGU2SmG"
  },
  "sort": 100000,
  "ownership": {
    "default": 0
  },
  "_key": "!items!HAV5XHqgTKQ36Liz"
}