{
  "folder": "tKBdn5Xs6o3Kzt2M",
  "name": "Oorah!",
  "type": "perk",
  "_id": "7CuDik9Vtpou9iDJ",
  "img": "systems/essence20/assets/icons/items/perk.svg",
  "system": {
    "originalId": "",
    "description": "",
    "source": {
      "book": "Sgt Slaughter Sourcebook",
      "page": 15
    },
    "items": {},
    "advances": {
      "baseValue": 1,
      "canAdvance": false,
      "currentValue": 0,
      "increaseValue": 1
    },
    "canActivate": false,
    "choice": null,
    "choiceType": "none",
    "isRoleVariant": false,
    "hasChoice": false,
    "hasMorphedToughnessBonus": false,
    "numChoices": 1,
    "prerequisite": "",
    "selectionLimit": 1,
    "type": "faction",
    "value": 0,
    "version": "giJoe"
  },
  "effects": [
    {
      "name": "Oorah!",
      "img": "icons/svg/aura.svg",
      "origin": "Compendium.essence20.sgt_slaughter_sourcebook.Item.7CuDik9Vtpou9iDJ",
      "duration": {
        "startTime": null,
        "combat": null,
        "seconds": null,
        "rounds": null,
        "turns": null,
        "startRound": null,
        "startTurn": null
      },
      "disabled": false,
      "_id": "tNDcDFXib8EdY5V3",
      "type": "base",
      "system": {},
      "changes": [
        {
          "key": "system.defenses.toughness.bonus",
          "mode": 2,
          "value": "1",
          "priority": null
        },
        {
          "key": "system.defenses.willpower.bonus",
          "mode": 2,
          "value": "1",
          "priority": null
        }
      ],
      "description": "",
      "tint": "#ffffff",
      "transfer": true,
      "statuses": [],
      "sort": 0,
      "flags": {},
      "_stats": {
        "compendiumSource": null,
        "duplicateSource": null,
        "exportSource": null,
        "coreVersion": "13.344",
        "systemId": "essence20",
        "systemVersion": "4.6.5",
        "createdTime": 1748807677349,
        "modifiedTime": 1748807720399,
        "lastModifiedBy": "j6WWLUdptyfr6qBb"
      },
      "_key": "!items.effects!7CuDik9Vtpou9iDJ.tNDcDFXib8EdY5V3"
    }
  ],
  "sort": 0,
  "ownership": {
    "default": 0,
    "j6WWLUdptyfr6qBb": 3
  },
  "flags": {},
  "_stats": {
    "compendiumSource": null,
    "duplicateSource": null,
    "exportSource": null,
    "coreVersion": "13.344",
    "systemId": "essence20",
    "systemVersion": "4.6.5",
    "createdTime": 1748807660330,
    "modifiedTime": 1748807669598,
    "lastModifiedBy": "j6WWLUdptyfr6qBb"
  },
  "_key": "!items!7CuDik9Vtpou9iDJ"
}
