{
  "folder": "pym3j6CQx8YXpUGr",
  "name": "Hardened Armor",
  "type": "rolePoints",
  "_id": "ELRCpQpT3q1Our7p",
  "img": "systems/essence20/assets/icons/items/rolePoints.svg",
  "system": {
    "originalId": "",
    "description": "",
    "source": {
      "book": "Across the Stars",
      "page": 52
    },
    "bonus": {
      "defenseBonus": {
        "cleverness": false,
        "evasion": false,
        "toughness": true,
        "willpower": false
      },
      "increase": 1,
      "level20Value": null,
      "increaseLevels": [
        "level4",
        "level8",
        "level12",
        "level16"
      ],
      "startingValue": 1,
      "type": "defenseBonus",
      "value": 0
    },
    "isActivatable": false,
    "isActive": false,
    "powerCost": null,
    "resource": {
      "increase": null,
      "level20Value": null,
      "level20ValueIsUnlimited": false,
      "increaseLevels": [],
      "max": null,
      "startingMax": null,
      "value": null
    },
    "level20Value": null
  },
  "effects": [],
  "sort": 0,
  "ownership": {
    "default": 0,
    "TfzSCNLMDHUjSABQ": 3
  },
  "flags": {},
  "_stats": {
    "systemId": "essence20",
    "systemVersion": "4.1.2",
    "coreVersion": "13.344",
    "createdTime": 1714149074176,
    "modifiedTime": 1714612901876,
    "lastModifiedBy": "TfzSCNLMDHUjSABQ",
    "compendiumSource": null,
    "duplicateSource": null,
    "exportSource": null
  },
  "_key": "!items!ELRCpQpT3q1Our7p"
}
