{
  "folder": "V6NVXZq8t26cStnZ",
  "name": "Not Like That, Like This!",
  "type": "perk",
  "_id": "OrK3XyNIyJcorMxp",
  "img": "systems/essence20/assets/icons/items/perk.svg",
  "system": {
    "originalId": "",
    "description": "",
    "source": {
      "book": "Enigma of Combination",
      "page": 30
    },
    "prerequisite": "",
    "selectionLimit": 1,
    "type": "role"
  },
  "effects": [],
  "sort": 150000,
  "ownership": {
    "default": 0,
    "TfzSCNLMDHUjSABQ": 3
  },
  "flags": {},
  "_stats": {
    "systemId": "essence20",
    "systemVersion": "4.2.0",
    "coreVersion": "13.344",
    "createdTime": 1714393832072,
    "modifiedTime": 1714856136477,
    "lastModifiedBy": "VEn5sPQRoWgUw9qd",
    "compendiumSource": null,
    "duplicateSource": null,
    "exportSource": null
  },
  "_key": "!items!OrK3XyNIyJcorMxp"
}
