{
  "folder": "GNKNEi6DeX1MrVvC",
  "name": "Scramble Modulator",
  "type": "upgrade",
  "_id": "5o2qpfqpwRPeUBPA",
  "img": "systems/essence20/assets/icons/items/upgrade_weapon.svg",
  "system": {
    "originalId": "",
    "description": "",
    "source": {
      "book": "Enigma of Combination",
      "page": 53
    },
    "armorBonus": {
      "defense": "toughness",
      "value": 0
    },
    "availability": "restricted",
    "benefit": "",
    "traits": [],
    "type": "weapon",
    "prerequisite": "Sonic Damage"
  },
  "effects": [],
  "sort": 0,
  "ownership": {
    "default": 0,
    "TfzSCNLMDHUjSABQ": 3
  },
  "flags": {},
  "_stats": {
    "systemId": "essence20",
    "systemVersion": "4.1.2",
    "coreVersion": "13.344",
    "createdTime": 1714482510930,
    "modifiedTime": 1714482538641,
    "lastModifiedBy": "TfzSCNLMDHUjSABQ",
    "compendiumSource": null,
    "duplicateSource": null,
    "exportSource": null
  },
  "_key": "!items!5o2qpfqpwRPeUBPA"
}
