{
  "folder": "4oQXDiqamMPpzv37",
  "name": "Titanspark",
  "type": "influence",
  "_id": "DTY4VHtiCeUZ95pr",
  "img": "systems/essence20/assets/icons/items/influence.svg",
  "system": {
    "originalId": "",
    "description": "",
    "source": {
      "book": "Enigma of Combination",
      "page": 24
    },
    "items": {
      "cb78": {
        "uuid": "Compendium.essence20.enigma_of_combination.Item.ldnUTXw5w21toLIy",
        "img": "systems/essence20/assets/icons/items/perk.svg",
        "name": "Titanspark",
        "type": "perk"
      },
      "3f24": {
        "uuid": "Compendium.essence20.enigma_of_combination.Item.duMjTyfREHYmDFJs",
        "img": "icons/svg/hazard.svg",
        "name": "Arrogant",
        "type": "hangUp"
      },
      "79aa": {
        "uuid": "Compendium.essence20.tf_crb.Item.V5GfafYii5GSMtzr",
        "img": "icons/svg/hazard.svg",
        "name": "Impulsive",
        "type": "hangUp"
      },
      "204b": {
        "uuid": "Compendium.essence20.tf_crb.Item.aT1jR044JiN8tLQi",
        "img": "icons/svg/hazard.svg",
        "name": "Violent",
        "type": "hangUp"
      }
    },
    "bond": "",
    "mandatoryHangUp": false,
    "skills": []
  },
  "effects": [],
  "sort": 0,
  "ownership": {
    "default": 0,
    "TfzSCNLMDHUjSABQ": 3
  },
  "flags": {},
  "_stats": {
    "systemId": "essence20",
    "systemVersion": "4.1.2",
    "coreVersion": "11.315",
    "createdTime": 1714273614759,
    "modifiedTime": 1714273740663,
    "lastModifiedBy": "TfzSCNLMDHUjSABQ"
  },
  "_key": "!items!DTY4VHtiCeUZ95pr"
}