{
  "folder": "dZQznuv1y8t9ym3l",
  "name": "Promethea Security Shock Stick",
  "type": "weapon",
  "_id": "PS3XndcDXifia2cf",
  "img": "icons/svg/item-bag.svg",
  "system": {
    "originalId": "",
    "description": "",
    "source": {
      "book": "Through the Shattered Grid",
      "page": 31
    },
    "items": {
      "962e": {
        "uuid": "Compendium.essence20.through_the_shattered_grid.Item.mCSx51Kfna2dBBAo",
        "img": "systems/essence20/assets/icons/items/weapon_effect.svg",
        "name": "Promethea Security Shock Stick Effect",
        "type": "weaponEffect",
        "classification": {
          "skill": "might",
          "style": "melee"
        },
        "damageValue": 1,
        "damageType": "element",
        "numHands": 1,
        "numTargets": 1,
        "radius": 0,
        "range": {
          "min": null,
          "reachMultiplier": 1,
          "long": null,
          "value": null
        },
        "shiftDown": 0
      },
      "f81e": {
        "uuid": "Compendium.essence20.through_the_shattered_grid.Item.MtiQ7wZh4BA7xcUP",
        "img": "systems/essence20/assets/icons/items/weapon_effect.svg",
        "name": "Promethea Security Shock Stick Alternate Effect 1",
        "type": "weaponEffect",
        "classification": {
          "skill": "might",
          "style": "melee"
        },
        "damageValue": 1,
        "damageType": "stun",
        "numHands": 1,
        "numTargets": 1,
        "radius": 0,
        "range": {
          "min": null,
          "reachMultiplier": 1,
          "long": null,
          "value": null
        },
        "shiftDown": 0
      },
      "f60c": {
        "uuid": "Compendium.essence20.through_the_shattered_grid.Item.5GiZOJwamRzLti5A",
        "img": "systems/essence20/assets/icons/items/weapon_effect.svg",
        "name": "Promethea Security Shock Stick Alternate Effect 2",
        "type": "weaponEffect",
        "classification": {
          "skill": "might",
          "style": "melee"
        },
        "damageValue": 1,
        "damageType": "maneuver",
        "numHands": 1,
        "numTargets": 1,
        "radius": 0,
        "range": {
          "min": null,
          "reachMultiplier": 1,
          "long": null,
          "value": null
        },
        "shiftDown": 1
      }
    },
    "availability": "other",
    "classification": {
      "size": "sidearm"
    },
    "equipped": true,
    "requirements": {
      "custom": "",
      "skill": "athletics",
      "shift": "none"
    },
    "traits": [
      "blunt",
      "electric",
      "energy",
      "silent",
      "stun"
    ],
    "transformerMode": "modeBotMode",
    "upgradeTraits": [],
    "usesPerScene": null
  },
  "effects": [],
  "sort": 0,
  "ownership": {
    "default": 0,
    "VEn5sPQRoWgUw9qd": 3
  },
  "flags": {},
  "_stats": {
    "compendiumSource": null,
    "duplicateSource": null,
    "coreVersion": "13.344",
    "systemId": "essence20",
    "systemVersion": "4.5.0",
    "createdTime": 1733701778109,
    "modifiedTime": 1733701843351,
    "lastModifiedBy": "VEn5sPQRoWgUw9qd",
    "exportSource": null
  },
  "_key": "!items!PS3XndcDXifia2cf"
}
